
{
  "networks": {
      "mainnet": {
              "contracts": {
                "_0xbitcointoken": {"name":"0xBitcoinToken", "blockchain_address":"0xb6ed7644c69416d67b522e20bc294a9a9b405b31"},
                "batchedpayments": {"name":"BatchedPayments", "blockchain_address":"0xebf6245689194a6e43096551567827c6726ede0b"},
                "mintforwarder":{"name":"MintHelper", "blockchain_address":"0xeabe48908503b7efb090f35595fb8d1a4d55bd66"},
                "miningking":{"name":"MiningKing", "blockchain_address":"0x0b98f937f6edd6f66b0f0a210d3dcd8ec1063cb6"},
                "doubleKingsReward":{"name":"DoubleKingsReward", "blockchain_address":"0xfd6be1247a5d32ee83aad9d1b09b5df9e2988d6f"}



              }
            },
      "staging": {
              "contracts": {
                "_0xbitcointoken": {"name":"0xBitcoinToken", "blockchain_address":"0x176762d66f15ccdd0d3a1dc13040d794c9c93776"},
                "batchedpayments": {"name":"BatchedPayments", "blockchain_address":"0x8abA3900567Dff202b634eCf98E71A6Dd251daF7"},
                "mintforwarder":{"name":"MintHelper", "blockchain_address":"0xeabe48908503b7efb090f35595fb8d1a4d55bd66"},
                "miningking":{"name":"MiningKing", "blockchain_address":"0x0b98f937f6edd6f66b0f0a210d3dcd8ec1063cb6"},
                "doubleKingsReward":{"name":"DoubleKingsReward", "blockchain_address":"0x40e690e430710cfca6583b24d8c187b85b7fc1a7"}
              }
            },
      "testnet": {
              "contracts": {
                "_0xbitcointoken": {"name":"0xBitcoinToken", "blockchain_address":"0x4fb6715cf6118746c1f08f1d739e17f2b12aaba8"},
                "batchedpayments": {"name":"BatchedPayments", "blockchain_address":"0x8abA3900567Dff202b634eCf98E71A6Dd251daF7"},

                "mintforwarder":{"name":"MintHelper", "blockchain_address":"0x6ffcad89b80bfa3064437c3fbaefef31b1e90f85"},

                "miningking":{"name":"MiningKing", "blockchain_address":"0x2a20403757ffa6b4e5c613026b7a7308f8722db7"},
                "doubleKingsReward":{"name":"DoubleKingsReward", "blockchain_address":"0x40e690e430710cfca6583b24d8c187b85b7fc1a7"}
              }
            }
    }
}
